textfeatureinfo/__init__.py
textfeatureinfo/textfeatureinfo.py
textfeatureinfo-0.2.8.dist-info/LICENSE
textfeatureinfo-0.2.8.dist-info/WHEEL
textfeatureinfo-0.2.8.dist-info/METADATA
textfeatureinfo-0.2.8.dist-info/RECORD
