Metadata-Version: 2.1
Name: textfeatureinfo
Version: 0.2.8
Summary: Package to extract interesting details about text.
License: MIT
Author: Kiran, Jacqueline, Paniz, Lynn
Requires-Python: >=3.9,<4.0
Classifier: License :: OSI Approved :: MIT License
Classifier: Programming Language :: Python :: 3
Classifier: Programming Language :: Python :: 3.10
Classifier: Programming Language :: Python :: 3.9
Requires-Dist: nltk (>=3.6.7,<4.0.0)
